odoo/addons/tracking_manager/README.rst
odoo/addons/tracking_manager/__init__.py
odoo/addons/tracking_manager/__manifest__.py
odoo/addons/tracking_manager/tools.py
odoo/addons/tracking_manager/i18n/es.po
odoo/addons/tracking_manager/i18n/fr.po
odoo/addons/tracking_manager/i18n/it.po
odoo/addons/tracking_manager/i18n/tracking_manager.pot
odoo/addons/tracking_manager/migrations/14.0.1.1.0/pre-fix-none-trackable-field.py
odoo/addons/tracking_manager/migrations/14.0.1.1.1/post-migration.py
odoo/addons/tracking_manager/models/__init__.py
odoo/addons/tracking_manager/models/ir_model.py
odoo/addons/tracking_manager/models/mail_thread.py
odoo/addons/tracking_manager/models/mail_tracking_value.py
odoo/addons/tracking_manager/models/models.py
odoo/addons/tracking_manager/readme/CONTRIBUTORS.rst
odoo/addons/tracking_manager/readme/DESCRIPTION.rst
odoo/addons/tracking_manager/readme/USAGE.rst
odoo/addons/tracking_manager/static/description/fields.png
odoo/addons/tracking_manager/static/description/icon.png
odoo/addons/tracking_manager/static/description/index.html
odoo/addons/tracking_manager/static/description/model_view.png
odoo/addons/tracking_manager/tests/__init__.py
odoo/addons/tracking_manager/tests/models.py
odoo/addons/tracking_manager/tests/test_tracking_manager.py
odoo/addons/tracking_manager/views/ir_model.xml
odoo/addons/tracking_manager/views/ir_model_fields.xml
odoo/addons/tracking_manager/views/message_template.xml
odoo14_addon_tracking_manager-14.0.1.3.0.dist-info/METADATA
odoo14_addon_tracking_manager-14.0.1.3.0.dist-info/WHEEL
odoo14_addon_tracking_manager-14.0.1.3.0.dist-info/top_level.txt
odoo14_addon_tracking_manager-14.0.1.3.0.dist-info/RECORD
